odoo8_addon_purchase_stock_analysis-8.0.1.0.0.99.dev3-py2.7-nspkg.pth
odoo8_addon_purchase_stock_analysis-8.0.1.0.0.99.dev3.dist-info/METADATA
odoo8_addon_purchase_stock_analysis-8.0.1.0.0.99.dev3.dist-info/RECORD
odoo8_addon_purchase_stock_analysis-8.0.1.0.0.99.dev3.dist-info/WHEEL
odoo8_addon_purchase_stock_analysis-8.0.1.0.0.99.dev3.dist-info/namespace_packages.txt
odoo8_addon_purchase_stock_analysis-8.0.1.0.0.99.dev3.dist-info/top_level.txt
odoo_addons/purchase_stock_analysis/README.rst
odoo_addons/purchase_stock_analysis/__init__.py
odoo_addons/purchase_stock_analysis/__openerp__.py
odoo_addons/purchase_stock_analysis/i18n/de.po
odoo_addons/purchase_stock_analysis/i18n/fr.po
odoo_addons/purchase_stock_analysis/model/__init__.py
odoo_addons/purchase_stock_analysis/model/purchase_stock_analysis.py
odoo_addons/purchase_stock_analysis/security/ir.model.access.csv
odoo_addons/purchase_stock_analysis/static/description/icon.png
odoo_addons/purchase_stock_analysis/view/purchase_stock_analysis.xml
