Metadata-Version: 2.1
Name: odoo8-addon-purchase-stock-analysis
Version: 8.0.1.0.0.99.dev3
Summary: Purchase Stock Analysis
Home-page: http://www.camptocamp.com
Author: Camptocamp,Odoo Community Association (OCA)
Author-email: support@odoo-community.org
License: UNKNOWN
Platform: UNKNOWN
Classifier: Programming Language :: Python
Classifier: Framework :: Odoo
Requires-Python: ~=2.7
Requires-Dist: odoo (<9.0a,>=8.0a)
